{
  "uid" : "4224153072f6344d",
  "name" : "pushSettingsBar[Настройка]",
  "title" : "Push settings bar [Настройка]",
  "time" : {
    "start" : 1517823457270,
    "stop" : 1517823457364,
    "duration" : 94
  },
  "summary" : {
    "attachments" : 0,
    "steps" : 0
  },
  "failure" : null,
  "description" : null,
  "severity" : "NORMAL",
  "status" : "PASSED",
  "suite" : {
    "uid" : "a1bfd0f423b4ce0a",
    "name" : "Surefire suite : Surefire test",
    "title" : "Surefire suite : Surefire test"
  },
  "steps" : [ ],
  "attachments" : [ ],
  "issues" : [ ],
  "testIds" : [ ],
  "labels" : [ {
    "name" : "suite-name",
    "value" : "Surefire suite : Surefire test"
  }, {
    "name" : "language",
    "value" : "JAVA"
  }, {
    "name" : "host",
    "value" : "inv5423-pc"
  }, {
    "name" : "thread",
    "value" : "8904@inv5423-pc.main(1)"
  }, {
    "name" : "testSuite",
    "value" : "Surefire suite"
  }, {
    "name" : "framework",
    "value" : "TestNG"
  }, {
    "name" : "testMethod",
    "value" : "pushSettingsBar"
  }, {
    "name" : "testGroup",
    "value" : "Surefire test"
  }, {
    "name" : "suite-title",
    "value" : "Surefire suite : Surefire test"
  }, {
    "name" : "testClass",
    "value" : "stepDefinition.CheckAccountNumberBegins"
  } ],
  "parameters" : [ ]
}